mal/__init__.py
mal/api.py
mal/cli.py
mal/color.py
mal/commands.py
mal/core.py
mal/login.py
mal/setup.py
mal/utils.py
mal-0.4.0.dist-info/METADATA
mal-0.4.0.dist-info/RECORD
mal-0.4.0.dist-info/WHEEL
mal-0.4.0.dist-info/entry_points.txt
mal-0.4.0.dist-info/top_level.txt
