Metadata-Version: 2.1
Name: mal
Version: 0.4.0
Summary: A command line interface to your MyAnimeList profile
Home-page: https://github.com/ryukinix/mal
Author: Manoel Vilela
Author-email: manoel_vilela@engineer.com
License: GPL
Download-URL: https://github.com/ryukinix/mal/archive/v0.4.0.tar.gz
Keywords: mal myanimelist cli anime manager
Platform: unix
Classifier: Environment :: Console
Classifier: Development Status :: 4 - Beta
Classifier: Intended Audience :: End Users/Desktop
Classifier: Topic :: Internet
Classifier: Topic :: Games/Entertainment
Classifier: Topic :: Utilities
Classifier: Operating System :: Unix
Classifier: Programming Language :: Python :: 3
Classifier: Programming Language :: Python :: 3.4
Classifier: Programming Language :: Python :: 3.5
Classifier: Programming Language :: Python :: 3.6
Classifier: License :: OSI Approved :: GNU General Public License v3 (GPLv3)
Provides-Extra: Requires-Dist
Requires-Dist: requests (>=2.18.1)
Requires-Dist: appdirs (>=1.4.0)
Requires-Dist: decorating (==0.6.1)
Provides-Extra: Requires-Dist
Requires-Dist: pypandoc; extra == 'Requires-Dist'
